hydra_cli/__init__.py
hydra_cli/__main__.py
hydra_cli/cli.py
hydra_cli/config.py
hydra_cli/docker.py
hydra_cli/main.py
hydra_cli-0.0.4.dist-info/METADATA
hydra_cli-0.0.4.dist-info/WHEEL
hydra_cli-0.0.4.dist-info/entry_points.txt
hydra_cli-0.0.4.dist-info/licenses/LICENSE
hydra_cli-0.0.4.dist-info/RECORD
