Metadata-Version: 2.4
Name: hydra-cli
Version: 0.0.4
Summary: Hydra CLI
Project-URL: Homepage, https://pypi.org/project/hydra-cli/
Project-URL: Documentation, https://docs.hydra.so/guides/local_development
Project-URL: Repository, https://github.com/hydradatabase/hydra-cli
Project-URL: Issues, https://github.com/hydradatabase/hydra-cli/issues
Author-email: Jonathan Dance <jd+pypi@wuputah.com>
License-File: LICENSE
Classifier: License :: OSI Approved :: MIT License
Classifier: Operating System :: OS Independent
Classifier: Programming Language :: Python :: 3
Requires-Python: >=3.8
Requires-Dist: docker
Requires-Dist: platformdirs
Requires-Dist: toml
